pydantic_mongo_document/__init__.py
pydantic_mongo_document/compat.py
pydantic_mongo_document/config.py
pydantic_mongo_document/cursor.py
pydantic_mongo_document/document/__init__.py
pydantic_mongo_document/document/asyncio.py
pydantic_mongo_document/document/base.py
pydantic_mongo_document/document/sync.py
pydantic_mongo_document/encoder.py
pydantic_mongo_document/exceptions.py
pydantic_mongo_document/misc.py
pydantic_mongo_document/py.typed
pydantic_mongo_document/types.py
pydantic_mongo_document-2.0.5.dist-info/LICENCE
pydantic_mongo_document-2.0.5.dist-info/METADATA
pydantic_mongo_document-2.0.5.dist-info/WHEEL
pydantic_mongo_document-2.0.5.dist-info/RECORD
