Metadata-Version: 2.1
Name: pydantic-mongo-document
Version: 2.0.5
Summary: Pydantic Async Mongo Document
License: MIT
Author: Yury Sokov (Yurzs)
Author-email: me@yurzs.dev
Requires-Python: >=3.11,<4.0
Classifier: License :: OSI Approved :: MIT License
Classifier: Programming Language :: Python :: 3
Classifier: Programming Language :: Python :: 3.11
Classifier: Programming Language :: Python :: 3.12
Classifier: Programming Language :: Python :: 3.13
Requires-Dist: pydantic (>=2.3.0,<3.0.0)
Requires-Dist: pymongo (>=4.9,<5.0)
